arvindfunny/__init__.py
arvindfunny-0.1.dist-info/DESCRIPTION.rst
arvindfunny-0.1.dist-info/METADATA
arvindfunny-0.1.dist-info/RECORD
arvindfunny-0.1.dist-info/WHEEL
arvindfunny-0.1.dist-info/metadata.json
arvindfunny-0.1.dist-info/top_level.txt
funny/__init__.py
