Metadata-Version: 2.0
Name: arvindfunny
Version: 0.1
Summary: Gives you funny jokes
Home-page: https://github.com/Arvind17/funny
Author: Arvind
Author-email: arvindsris@gmail.com
License: AIT
Platform: UNKNOWN
